{
    "13450": "Let's go! start!! Dengan melaju",
    "15770": "Di zaman kini ini",
    "19300": "Teruslah bersinar tanpa henti",
    "34670": "Saat mulainya perasaan debar ini, ku percaya",
    "40700": "Tak ada yang bisa hentikan ku berlari",
    "44920": "Di masa depan, ku bayangkan denganmu",
    "51080": "Bisa berlari kemana kita mau",
    "55450": "Ketika ku kurang percaya diri dan merasa lemah",
    "60520": "Akan kuingat rasanya momen itu",
    "62920": "Dan percaya hati kita kembali semangat",
    "67930": "Let's go! start!! Dengan melaju di zaman kini ini",
    "73780": "Teruslah bersinar tanpa henti",
    "78530": "Tak tahu (tak tahu), namun ingin tahu (ingin tahu)\nbahwa aku tak menyerah lagi",
    "83867": "Dengan merangkul harapan dan mimpi (Coba lagi)",
    "88780": "Mari terbang tinggi dengan melompat\ndan melihat kedepan",
    "94530": "Ambillah langkah pertama kita",
    "99570": "Kapanpun (Saat) semuanya (bersama)\ntelah menunggumu",
    "104620": "Di panggung impian yang dibaluti Sihir"
}