{
  "no_wrap": true,
  "text_block_list": [
    {
      "text": "…………",
      "name": "Special Week"
    },
    {
      "text": "……Grass Wonder emang kuat banget, tapi tetep aja Spe, kamu udah lari bagus kok.",
      "name": "<username>"
    },
    {
      "text": "……Iya.",
      "name": "Special Week"
    },
    {
      "text": "Haa……Haaa……Haaa……Haaa……Haaaa!",
      "name": "El Condor Pasa"
    },
    {
      "text": "Sppuuuuuuurtーー!!",
      "name": "El Condor Pasa"
    },
    {
      "text": "Haa……Haaa……Huuu～……",
      "name": "El Condor Pasa"
    },
    {
      "text": "(Kring! Kring!)"
    },
    {
      "text": "Allo～!? Bonjouuuur!",
      "name": "El Condor Pasa"
    },
    {
      "text": "『Halo, El. Lagi latihan ya barusan?』",
      "name": "Grass Wonder"
    },
    {
      "text": "Aku baru mau istirahat! Perutku udah keroncongan!",
      "name": "El Condor Pasa"
    },
    {
      "text": "『Fufuu, syukurlah kedengerannya kamu baik-baik aja』",
      "name": "Grass Wonder"
    },

    {
      "text": "『Wah, aku terhormat kamu mikir gitu』",
      "name": "Grass Wonder"
    },
 
    {
      "text": "『Woooow! Kayak biasa ya, semangat bertarungmu tetep menyala-nyala!』",
      "name": "El Condor Pasa"
    },
    {
      "text": "……El juga, bentar lagi waktunya kamu nantangin yang terkuat.",
      "name": "Grass Wonder"
    },
  
    {
      "text": "Terus mimpiku――Aku bakal buktiin kalau aku emang yang terkuat di dunia!!",
      "name": "El Condor Pasa"
    },
    {
      "text": "『……Kalau kamu semangatnya gitu, kayanya kamu bisa kasih segalanya』",
      "name": "Grass Wonder"
    },
    {
      "text": "Segalanya ya――",
      "name": "El Condor Pasa"
    },
    {
      "text": "Semuanya! Makasih udah nganterin aku, aku jadi makin semangat dan terharu!",
      "name": "El Condor Pasa"
    },
    {
      "text": "Beneran nggak apa-apa kita nggak nganterin ke bandara?",
      "name": "Special Week"
    },
    {
      "text": "Bueno! Hari ini hari biasa kan? Kalian harus belajar yang rajin!",
      "name": "El Condor Pasa"
    },
  
    {
      "text": "Punya temen sekelas yang nantang dunia tuh rasanya bikin bangga juga sih.",
      "name": "King Halo"
    },
   
    {
      "text": "Ehehe, aku bakal berusaha keras!",
      "name": "El Condor Pasa"
    },
    {
      "text": "Kalau gitu……aku berangkat ya……",
      "name": "El Condor Pasa"
    },
    {
      "text": "Beneran……aku harus berangkat……",
      "name": "El Condor Pasa"
    },
    {
      "text": "…………",
      "name": "Grass Wonder"
    },
    {
      "text": "……El, kamu masih ada waktu dikit lagi kan?",
      "name": "Grass Wonder"
    },
    {
      "text": "Que……?",
      "name": "El Condor Pasa"
    },
    {
      "text": "Fufuu, kalau gitu, biar aku kasih semangat――",
      "name": "Grass Wonder"
    },
    {
      "text": "Apaan iniii～～!?",
      "name": "El Condor Pasa"
    },
  
    {
      "text": "Jadi gini caranya kita nganterin dia ya? Fufuu, menarik juga!",
      "name": "King Halo"
    },
   
    {
      "text": "Aku juga! Daaaaaaa～～!",
      "name": "Special Week"
    },
    {
      "text": "Oh～ oh～, makin panas aja nih suasananya～?",
      "name": "Seiun Sky"
    },
    {
      "text": "Eh bentar!? Kita beneran lari!?",
      "name": "El Condor Pasa"
    },
    {
      "text": "Haaa……haaa……El, tolong tunjukkin ke kita.",
      "name": "Grass Wonder"
    },
    {
      "text": "Larinya seseorang yang ngejar gelar terkuat di dunia, tunjukkin……!",
      "name": "Grass Wonder"
    },
    {
      "text": "……！",
      "name": "El Condor Pasa"
    },
  
    {
      "text": "Liat aja aku! Yaaaaaaa～～～～!!",
      "name": "El Condor Pasa"
    },
   
    {
      "text": "『Iya, pastiin kamu kasih pertunjukan yang hebat ya』",
      "name": "Grass Wonder"
    },
    {
      "text": "『Dan setelah itu……aku nggak sabar buat balapan bareng El yang itu♪』",
      "name": "Grass Wonder"
    },
    {
      "text": "Ehehe, iya!",
      "name": "El Condor Pasa"
    },
  
    {
      "text": "…………",
      "name": "El Condor Pasa"
    },

    
    {
      "text": "(……Mimpiku, buktiin kalau aku yang terkuat di dunia, di panggung ini……)",
      "name": "El Condor Pasa"
    },
    {
      "text": "Dan inilah, Uma Musume yang paling ditunggu-tunggu masuk ke paddock!",
      "name": "Penyiar"
    },
  
    {
      "text": "……Fuu.",
      "name": "Montjeu"
    },
    {
      "text": "Montjeu……",
      "name": "El Condor Pasa"
    },
   
    {
      "text": "Kekuatan sejati Uma Musume Jepang, tunjukkin ke aku di sini.",
      "name": "Montjeu"
    },
    {
      "text": "Nggak usah disuruh, aku bakal tunjukkin lebih dari itu……!",
      "name": "El Condor Pasa"
    },
    {
      "text": "<Mari kita kasih balapan terbaik>",
      "name": "Montjeu"
    }
  
  ]
}